D_latch_struct.v
module mux2to1(in,sel,out);
input[1:0] in;
input sel;
output out;
wire t1,t2,t3;
not G1(t1,sel);
and G2(t2,in[0],t1);
and G3(t3,in[1],sel);
or G4(out,t2,t3);
endmodule
module D_latch(D,E,Q,Qbar);
input D,E;
output Q,Qbar;
wire[1:0] in;
assign in[1]=Q;
assign in[0]=D;
assign Qbar=~Q;
mux2to1 M0(in,E,Q);
endmodule

D_latch_test.v
module D_latch_test;
reg D,E;
wire Q,Qbar;
D_latch DUT(D,E,Q,Qbar);
initial begin
    $dumpfile("D_latch.vcd");
    $dumpvars(0,D_latch_test);
    $monitor($time,"D=%b,E=%b,Q=%b,Qbar=%b",D,E,Q,Qbar);
    #5 D=1;E=1;
    #5 D=0;E=0;
    #5 D=0;E=1;
    #5 D=1;E=0;
    #5 D=1;E=1;
    #5 D=0;E=0;
    #5 D=0;E=1;
    #5 D=1;E=0;
end
endmodule

D_latch.vcd
$date
	Tue May 11 22:33:59 2021
$end
$version
	Icarus Verilog
$end
$timescale
	1s
$end
$scope module D_latch_test $end
$var wire 1 ! Qbar $end
$var wire 1 " Q $end
$var reg 1 # D $end
$var reg 1 $ E $end
$scope module DUT $end
$var wire 1 # D $end
$var wire 1 $ E $end
$var wire 1 ! Qbar $end
$var wire 2 % in [1:0] $end
$var wire 1 " Q $end
$scope module M0 $end
$var wire 2 & in [1:0] $end
$var wire 1 " out $end
$var wire 1 $ sel $end
$var wire 1 ' t1 $end
$var wire 1 ( t2 $end
$var wire 1 ) t3 $end
$upscope $end
$upscope $end
$upscope $end
$enddefinitions $end
#0
$dumpvars
x)
x(
x'
bx &
bx %
x$
x#
x"
x!
$end
#5
0(
0'
1$
bx1 %
bx1 &
1#
#10
1!
0"
1'
0)
0$
b0 %
b0 &
0#
#15
0'
1$
#20
0!
1"
1(
1'
0$
b11 %
b11 &
1#
#25
0(
0'
1)
1$
#30
1!
0"
1'
0)
0$
b0 %
b0 &
0#
#35
0'
1$
#40
0!
1"
1(
1'
0$
b11 %
b11 &
1#
