Division_seq.v
module Division_seq(Divisor,Dividend,Quotient,Reminder,clk,ready);
parameter N = 8;
input [N-1:0] Divisor,Dividend;
input clk,ready;
output reg[N-1:0] Quotient,Reminder;
reg[2*N-1:0] Q;
reg[3:0] count;
reg res;
always @(posedge ready) begin
    Q={8'b0,Dividend};
    count=0;
    res=1'b0;
end
always @(posedge res) begin
    Quotient=Q[N-1:0];
    Reminder=Q[2*N-1:N];
end
always @(posedge clk) begin
    if(count<8)begin
      Q=Q<<1;
      if(Q[2*N-1:N]>=Divisor)begin
        Q[2*N-1:N]=Q[2*N-1:N]-Divisor;
        Q[0]=1'b1;
      end
      else begin
        Q[0]=1'b0;
      end
      count=count+1;
    end
    else begin
      res=1'b1;
    end
end
endmodule

Division_seq_test.v
module Division_seq_test;
reg[7:0] Divisor,Dividend;
wire[7:0] Quotient,Reminder;
reg ready,clk;
Division_seq DUT(Divisor,Dividend,Quotient,Reminder,clk,ready);
initial begin
 clk=1'b0;
    ready=1'b0;
     #2 ready=1'b1; 
     Dividend=8'b10000101;
      Divisor=8'b10001;
    #10 ready=1'b0;
      #200 $finish;
end
always #5 clk=~clk;
initial begin
    $dumpfile("Division_seq_test.vcd");
    $dumpvars(0,Division_seq_test);
end
endmodule

Division_seq_test.vcd
$date
	Sun Feb  6 21:56:59 2022
$end
$version
	Icarus Verilog
$end
$timescale
	1s
$end
$scope module Division_seq_test $end
$var wire 8 ! Reminder [7:0] $end
$var wire 8 " Quotient [7:0] $end
$var reg 8 # Dividend [7:0] $end
$var reg 8 $ Divisor [7:0] $end
$var reg 1 % clk $end
$var reg 1 & ready $end
$scope module DUT $end
$var wire 8 ' Dividend [7:0] $end
$var wire 8 ( Divisor [7:0] $end
$var wire 1 % clk $end
$var wire 1 & ready $end
$var reg 16 ) Q [15:0] $end
$var reg 8 * Quotient [7:0] $end
$var reg 8 + Reminder [7:0] $end
$var reg 4 , count [3:0] $end
$var reg 1 - res $end
$upscope $end
$upscope $end
$enddefinitions $end
#0
$dumpvars
x-
bx ,
bx +
bx *
bx )
bx (
bx '
0&
0%
bx $
bx #
bx "
bx !
$end
#2
0-
b0 ,
b10000101 )
b10001 $
b10001 (
b10000101 #
b10000101 '
1&
#5
b1 ,
b100001010 )
1%
#10
0%
#12
0&
#15
b10 ,
b1000010100 )
1%
#20
0%
#25
b11 ,
b10000101000 )
1%
#30
0%
#35
b100 ,
b100001010000 )
1%
#40
0%
#45
b101 ,
b1000010100000 )
1%
#50
0%
#55
b110 ,
b1000001000001 )
1%
#60
0%
#65
b111 ,
b111110000011 )
1%
#70
0%
#75
b1000 ,
b111000000111 )
1%
#80
0%
#85
b1110 !
b1110 +
b111 "
b111 *
1-
1%
