FPDS_32.v
module Encoder(A,res);
parameter N = 24;
input[N-1:0] A;
output reg[4:0] res;
integer n;
always @(*) begin
    for(n=0;n<24;n=n+1)
    if(A[n])res=n;
end
endmodule
module adjust_mantissa(A,B,A_out,B_out);
parameter N =24;
input[N-1:0] A,B;
output [N-1:0] A_out,B_out;
wire[N-1:0] temp_A,temp_B;
wire[4:0] temp_res_A,temp_res_B;
//reg[N-1:0] temp_reg_A,temp_reg_B;
assign temp_A=A ^ (A&(A-1));
assign temp_B=B ^ (B&(B-1));
Encoder E1(temp_A,temp_res_A);
Encoder E2(temp_B,temp_res_B);
assign A_out=A>>temp_res_A;
assign B_out=B>>temp_res_B;
endmodule
module Division_seq(Divisor,Dividend,Quotient,clk,ready);
parameter N = 24;
input [N-1:0] Divisor,Dividend;
input clk,ready;
output reg[N-1:0] Quotient;
//,Reminder;
reg[2*N-1:0] Q;
reg[4:0] count;
reg res;
always @(posedge ready) begin
    Q={24'b0,Dividend};
    count=0;
    res=1'b0;
end
always @(posedge res) begin
    Quotient=Q[N-1:0];
  //  Reminder=Q[2*N-1:N];
end
always @(posedge clk) begin
    if(count<24)begin
      Q=Q<<1;
      if(Q[2*N-1:N]>=Divisor)begin
        Q[2*N-1:N]=Q[2*N-1:N]-Divisor;
        Q[0]=1'b1;
      end
      else begin
        Q[0]=1'b0;
      end
      count=count+1;
    end
    else begin
      res=1'b1;
    end
end
endmodule
module flip_bits(A,B);
parameter N = 24;
input[N-1:0] A;
output reg[N-1:0] B;
integer n;
always @(*) begin
for(n=23;n>=0;n=n-1)begin
B[n]=A[23-n];
end
end
endmodule
module Exponent_sub(Dividend_exponent,Divisor_exponent,exponent_out);
input[7:0] Dividend_exponent,Divisor_exponent;
output reg[7:0] exponent_out;
always @(*) begin
  exponent_out=Dividend_exponent-Divisor_exponent+8'b01111111;
end
endmodule
module Foloating_point_Division(Divisor,Dividend,Quotient,clk,ready);
parameter N = 24;
input [N-1:0] Divisor,Dividend;
input clk,ready;
output [N-2:0] Quotient;
wire [N-1:0] temp_Divisor,temp_Dividend,temp_Quotient,temp_rev_Q,temp,temp_Q;
wire[4:0] bit_shift;
adjust_mantissa AM(Divisor,Dividend,temp_Divisor,temp_Dividend);
Division_seq DS(temp_Divisor,temp_Dividend,temp_Quotient,clk,ready);
flip_bits FB(temp_Quotient,temp_rev_Q);
assign temp=temp_rev_Q ^ (temp_rev_Q &(temp_rev_Q-1));
Encoder E1(temp,bit_shift);
assign temp_Q=temp_Quotient<<bit_shift;
assign Quotient=temp_Q[N-2:0];
endmodule
module FPDS_32(Divisor,Dividend,Quotient,clk,ready);
input[31:0] Divisor,Dividend;
input clk,ready;
output [31:0] Quotient;
assign Quotient[31]=Dividend[31] ^ Divisor[31];
Exponent_sub E1(Dividend[30:23],Divisor[30:23],Quotient[30:23]);
Foloating_point_Division D1({1'b1,Divisor[22:0]},{1'b1,Dividend[22:0]},Quotient[22:0],clk,ready);
endmodule

FPDS_test.v
module FPDS_test;
reg[31:0] Divisor,Dividend;
reg clk,ready;
wire [31:0] Quotient;
FPDS_32 DUT(Divisor,Dividend,Quotient,clk,ready);
initial begin
    clk=1'b0;
     ready=1'b0;
      Dividend=32'b01000010101101101011000000000000; //91.34375
      Divisor=32'b00111110000101000000000000000000; //0.14453125
 //    Dividend=32'b00111111100000000000000000000000;
    //    Divisor=32'b01000000000000000000000000000000;
        #1 ready=1'b1;
    #300 ready=1'b0; 
    #305 ready=1'b1;
    //  Dividend=32'b00111111100000000000000000000000;
    //     Divisor=32'b01000000000000000000000000000000;
    #1000 $finish;
end
always #5 clk=~clk;
initial begin
    $dumpfile("FPDS_test.vcd");
    $dumpvars(0,FPDS_test);
end
endmodule

FPDS_test.vcd
$date
	Tue Feb  8 23:38:49 2022
$end
$version
	Icarus Verilog
$end
$timescale
	1s
$end
$scope module FPDS_test $end
$var wire 32 ! Quotient [31:0] $end
$var reg 32 " Dividend [31:0] $end
$var reg 32 # Divisor [31:0] $end
$var reg 1 $ clk $end
$var reg 1 % ready $end
$scope module DUT $end
$var wire 32 & Dividend [31:0] $end
$var wire 32 ' Divisor [31:0] $end
$var wire 1 $ clk $end
$var wire 1 % ready $end
$var wire 32 ( Quotient [31:0] $end
$scope module D1 $end
$var wire 24 ) Dividend [23:0] $end
$var wire 24 * Divisor [23:0] $end
$var wire 1 $ clk $end
$var wire 1 % ready $end
$var wire 24 + temp [23:0] $end
$var wire 24 , temp_rev_Q [23:0] $end
$var wire 24 - temp_Quotient [23:0] $end
$var wire 24 . temp_Q [23:0] $end
$var wire 24 / temp_Divisor [23:0] $end
$var wire 24 0 temp_Dividend [23:0] $end
$var wire 5 1 bit_shift [4:0] $end
$var wire 23 2 Quotient [22:0] $end
$scope module AM $end
$var wire 24 3 A [23:0] $end
$var wire 24 4 B [23:0] $end
$var wire 24 5 temp_A [23:0] $end
$var wire 24 6 temp_B [23:0] $end
$var wire 5 7 temp_res_B [4:0] $end
$var wire 5 8 temp_res_A [4:0] $end
$var wire 24 9 B_out [23:0] $end
$var wire 24 : A_out [23:0] $end
$scope module E1 $end
$var wire 24 ; A [23:0] $end
$var reg 5 < res [4:0] $end
$var integer 32 = n [31:0] $end
$upscope $end
$scope module E2 $end
$var wire 24 > A [23:0] $end
$var reg 5 ? res [4:0] $end
$var integer 32 @ n [31:0] $end
$upscope $end
$upscope $end
$scope module DS $end
$var wire 24 A Dividend [23:0] $end
$var wire 24 B Divisor [23:0] $end
$var wire 1 $ clk $end
$var wire 1 % ready $end
$var reg 48 C Q [47:0] $end
$var reg 24 D Quotient [23:0] $end
$var reg 5 E count [4:0] $end
$var reg 1 F res $end
$upscope $end
$scope module E1 $end
$var wire 24 G A [23:0] $end
$var reg 5 H res [4:0] $end
$var integer 32 I n [31:0] $end
$upscope $end
$scope module FB $end
$var wire 24 J A [23:0] $end
$var reg 24 K B [23:0] $end
$var integer 32 L n [31:0] $end
$upscope $end
$upscope $end
$scope module E1 $end
$var wire 8 M Dividend_exponent [7:0] $end
$var wire 8 N Divisor_exponent [7:0] $end
$var reg 8 O exponent_out [7:0] $end
$upscope $end
$upscope $end
$upscope $end
$enddefinitions $end
#0
$dumpvars
b10001000 O
b1111100 N
b10000101 M
bx L
bx K
bx J
bx I
bx H
bx G
xF
bx E
bx D
bx C
b100101 B
b101101101011 A
b11000 @
b1100 ?
b1000000000000 >
b11000 =
b10010 <
b1000000000000000000 ;
b100101 :
b101101101011 9
b10010 8
b1100 7
b1000000000000 6
b1000000000000000000 5
b101101101011000000000000 4
b100101000000000000000000 3
bx 2
bx 1
b101101101011 0
b100101 /
bx .
bx -
bx ,
bx +
b100101000000000000000000 *
b101101101011000000000000 )
b10001000xxxxxxxxxxxxxxxxxxxxxxx (
b111110000101000000000000000000 '
b1000010101101101011000000000000 &
0%
0$
b111110000101000000000000000000 #
b1000010101101101011000000000000 "
b10001000xxxxxxxxxxxxxxxxxxxxxxx !
$end
#1
0F
b0 E
b101101101011 C
1%
#5
b1 E
b1011011010110 C
1$
#10
0$
#15
b10 E
b10110110101100 C
1$
#20
0$
#25
b11 E
b101101101011000 C
1$
#30
0$
#35
b100 E
b1011011010110000 C
1$
#40
0$
#45
b101 E
b10110110101100000 C
1$
#50
0$
#55
b110 E
b101101101011000000 C
1$
#60
0$
#65
b111 E
b1011011010110000000 C
1$
#70
0$
#75
b1000 E
b10110110101100000000 C
1$
#80
0$
#85
b1001 E
b101101101011000000000 C
1$
#90
0$
#95
b1010 E
b1011011010110000000000 C
1$
#100
0$
#105
b1011 E
b10110110101100000000000 C
1$
#110
0$
#115
b1100 E
b101101101011000000000000 C
1$
#120
0$
#125
b1101 E
b1011011010110000000000000 C
1$
#130
0$
#135
b1110 E
b10110110101100000000000000 C
1$
#140
0$
#145
b1111 E
b101101101011000000000000000 C
1$
#150
0$
#155
b10000 E
b1011011010110000000000000000 C
1$
#160
0$
#165
b10001 E
b10110110101100000000000000000 C
1$
#170
0$
#175
b10010 E
b1000101011000000000000000001 C
1$
#180
0$
#185
b10011 E
b10001010110000000000000000010 C
1$
#190
0$
#195
b10100 E
b100010101100000000000000000100 C
1$
#200
0$
#205
b10101 E
b100000011000000000000000001001 C
1$
#210
0$
#215
b10110 E
b11011110000000000000000010011 C
1$
#220
0$
#225
b10111 E
b10010100000000000000000100111 C
1$
#230
0$
#235
b11000 E
b1001111 C
1$
#240
0$
#245
b1000100000111100000000000000000 !
b1000100000111100000000000000000 (
b111100000000000000000 2
b100111100000000000000000 .
b10001 1
b10001 H
b11000 I
b100000000000000000 +
b100000000000000000 G
b111100100000000000000000 ,
b111100100000000000000000 K
b11111111111111111111111111111111 L
b1001111 -
b1001111 D
b1001111 J
1F
1$
#250
0$
#255
1$
#260
0$
#265
1$
#270
0$
#275
1$
#280
0$
#285
1$
#290
0$
#295
1$
#300
0$
#301
0%
