Contral_add.v
module PIPO1(dout,din,ld,clk);
input[15:0] din;
input ld,clk;
output reg[15:0] dout;
always @(posedge clk) 
begin
    if(ld)dout<=din;
end
endmodule

module PIPO2(dout,din,ld,clr,clk);
input[15:0] din;
input ld,clr,clk;
output reg[15:0] dout;
always @(posedge clk) begin
if(ld)dout<=din;
else if(clr)dout<=16'b0;    
end
endmodule

module add(out,in1,in2);
input[15:0] in1,in2;
output reg [15:0] out;
always @(*) begin
    out=in1+in2;
end
endmodule

module EQZ(din,e);
input[15:0] din;
output e;
assign e=(din==0);
endmodule
module CNTR(dout,din,ld,dec,clk);
input[15:0] din;
input ld,dec,clk;
output reg[15:0] dout;
always @(posedge clk) begin
    if(ld) dout<=din;
    else if(dec) dout<=dout-1;
end
endmodule
module MUL_datapath(eqz,lda,ldb,ldp,clrp,decb,data_in,clk);
input eqz,lda,ldb,ldp,clrp,decb,clk;
input[15:0] data_in;
wire [15:0] X,Y,Z,Bout,Bus;
assign Bus=data_in;
PIPO1 A(X,Bus,lda,clk);
PIPO2 B(Y,Z,ldp,clrp,clk);
add C(Z,X,Y);
CNTR D(Bout,Bus,ldb,decb,clk);
EQZ E(Bout,eqz);
endmodule
module controller(lda,ldb,ldp,clrp,decb,done,clk,eqz,start);
input clk,eqz,start;
output reg lda,ldb,ldp,clrp,decb,done;
reg[2:0] state;
parameter  S0=3'b000,S1=3'b001,S2=3'b010,S3=3'b011,S4=3'b100;
always @(posedge clk) begin
  case(state)
  S0:if(start)state<=S1;
  S1:state<=S2;
  S2:state<=S3;
  S3:#2 if(eqz) state<=S4;
  S4:state<=S4;
  default:state<=S0;
  endcase
end
always @(state) begin
    case(state)
    S0:begin #1 lda=0;ldb=0;ldp=0;clrp=0;decb=0;done=0;end
    S1:begin #1 lda=1;end
    S2:begin #1 lda=0;ldb=1;clrp=1;end
    S3:begin #1 ldb=0;ldp=1;clrp=0;decb=1;end
    S4:begin #1 done=1;ldb=0;ldp=0;decb=0;end
    default:begin #1 lda=0;ldb=0;ldp=0;clrp=0;decb=0;done=0;end
    endcase
end    
endmodule

Control_add_test.v
module Control_add_test;
reg[15:0] data_in;
reg clk,start;
wire done;
MUL_datapath DP(eqz,lda,ldb,ldp,clrp,decb,data_in,clk);
controller C(lda,ldb,ldp,clrp,decb,done,clk,eqz,start);
initial begin
    clk=1'b0;
    #3 start=1'b1;
    #500 $finish;
end
always #5 clk=~clk;
initial begin
    #17 data_in=17;
    #10 data_in=5;
end
initial begin
    $monitor($time,"%d %b",DP.Y,done);
    $dumpfile("mul.vcd");
    $dumpvars(0,Control_add_test);
end
endmodule

mul.vcd
$date
	Mon May 17 21:58:40 2021
$end
$version
	Icarus Verilog
$end
$timescale
	1s
$end
$scope module Control_add_test $end
$var wire 1 ! ldp $end
$var wire 1 " ldb $end
$var wire 1 # lda $end
$var wire 1 $ eqz $end
$var wire 1 % done $end
$var wire 1 & decb $end
$var wire 1 ' clrp $end
$var reg 1 ( clk $end
$var reg 16 ) data_in [15:0] $end
$var reg 1 * start $end
$scope module C $end
$var wire 1 ( clk $end
$var wire 1 * start $end
$var wire 1 $ eqz $end
$var reg 1 ' clrp $end
$var reg 1 & decb $end
$var reg 1 % done $end
$var reg 1 # lda $end
$var reg 1 " ldb $end
$var reg 1 ! ldp $end
$var reg 3 + state [2:0] $end
$upscope $end
$scope module DP $end
$var wire 16 , Bus [15:0] $end
$var wire 1 ( clk $end
$var wire 1 ' clrp $end
$var wire 16 - data_in [15:0] $end
$var wire 1 & decb $end
$var wire 1 # lda $end
$var wire 1 " ldb $end
$var wire 1 ! ldp $end
$var wire 1 $ eqz $end
$var wire 16 . Z [15:0] $end
$var wire 16 / Y [15:0] $end
$var wire 16 0 X [15:0] $end
$var wire 16 1 Bout [15:0] $end
$scope module A $end
$var wire 1 ( clk $end
$var wire 16 2 din [15:0] $end
$var wire 1 # ld $end
$var reg 16 3 dout [15:0] $end
$upscope $end
$scope module B $end
$var wire 1 ( clk $end
$var wire 1 ' clr $end
$var wire 1 ! ld $end
$var wire 16 4 din [15:0] $end
$var reg 16 5 dout [15:0] $end
$upscope $end
$scope module C $end
$var wire 16 6 in1 [15:0] $end
$var wire 16 7 in2 [15:0] $end
$var reg 16 8 out [15:0] $end
$upscope $end
$scope module D $end
$var wire 1 ( clk $end
$var wire 1 & dec $end
$var wire 16 9 din [15:0] $end
$var wire 1 " ld $end
$var reg 16 : dout [15:0] $end
$upscope $end
$scope module E $end
$var wire 16 ; din [15:0] $end
$var wire 1 $ e $end
$upscope $end
$upscope $end
$upscope $end
$enddefinitions $end
#0
$dumpvars
bx ;
bx :
bx 9
bx 8
bx 7
bx 6
bx 5
bx 4
bx 3
bx 2
bx 1
bx 0
bx /
bx .
bx -
bx ,
bx +
x*
bx )
0(
x'
x&
x%
x$
x#
x"
x!
$end
#3
1*
#5
b0 +
1(
#6
0%
0&
0'
0!
0"
0#
#10
0(
#15
b1 +
1(
#16
1#
#17
b10001 ,
b10001 2
b10001 9
b10001 )
b10001 -
#20
0(
#25
b10001 0
b10001 3
b10001 6
b10 +
1(
#26
1'
1"
0#
#27
b101 ,
b101 2
b101 9
b101 )
b101 -
#30
0(
#35
b10001 .
b10001 4
b10001 8
b11 +
0$
b101 1
b101 :
b101 ;
b0 /
b0 5
b0 7
1(
#36
1&
0'
1!
0"
#40
0(
#45
b100010 .
b100010 4
b100010 8
b10001 /
b10001 5
b10001 7
b100 1
b100 :
b100 ;
1(
#50
0(
#55
b110011 .
b110011 4
b110011 8
b11 1
b11 :
b11 ;
b100010 /
b100010 5
b100010 7
1(
#60
0(
#65
b1000100 .
b1000100 4
b1000100 8
b110011 /
b110011 5
b110011 7
b10 1
b10 :
b10 ;
1(
#70
0(
#75
b1010101 .
b1010101 4
b1010101 8
b1 1
b1 :
b1 ;
b1000100 /
b1000100 5
b1000100 7
1(
#80
0(
#85
b1100110 .
b1100110 4
b1100110 8
b1010101 /
b1010101 5
b1010101 7
1$
b0 1
b0 :
b0 ;
1(
#87
b100 +
#88
0&
0!
1%
